ezfile/__init__.py
ezfile/ezfile.py
ezfile-0.0.3.4.dist-info/DESCRIPTION.rst
ezfile-0.0.3.4.dist-info/METADATA
ezfile-0.0.3.4.dist-info/RECORD
ezfile-0.0.3.4.dist-info/WHEEL
ezfile-0.0.3.4.dist-info/metadata.json
ezfile-0.0.3.4.dist-info/top_level.txt
