Metadata-Version: 2.0
Name: ezfile
Version: 0.0.3.4
Summary: A one-line file-IO package
Home-page: https://github.com/moe001/ezfile
Author: moe001
Author-email: i@001.moe
License: MIT
Platform: UNKNOWN
